{"cameraMode":{"drawMode":0,"name":"Shaded","section":"Shading Mode"},"sceneLighting":true,"audioPlay":false,"sceneViewState":{"m_AlwaysRefresh":false,"showFog":true,"showSkybox":true,"showFlares":true,"showImageEffects":true,"showParticleSystems":true,"showVisualEffectGraphs":true,"m_FxEnabled":true},"in2DMode":false,"pivot":{"x":5.621284484863281,"y":0.5822563171386719,"z":14.42760944366455},"rotation":{"x":-0.23376992344856263,"y":0.6662926077842712,"z":-0.23292900621891023,"w":-0.6686962842941284},"size":15.412703514099121,"orthographic":false}